annuairesante_fhir/__init__.py
annuairesante_fhir/client.py
annuairesante_fhir/dynamic_helper.py
annuairesante_fhir/exceptions.py
annuairesante_fhir/helpers.py
annuairesante_fhir/models.py
annuairesante_fhir/mos_downloader.py
annuairesante_fhir/mos_resolver.py
annuairesante_fhir/sub_helpers.py
annuairesante_fhir/resources/__init__.py
annuairesante_fhir/resources/base.py
annuairesante_fhir/resources/device.py
annuairesante_fhir/resources/healthcare_service.py
annuairesante_fhir/resources/organization.py
annuairesante_fhir/resources/practitioner.py
annuairesante_fhir/resources/practitioner_role.py
annuairesante_fhir_client-0.2.1.dist-info/licenses/LICENSE
annuairesante_fhir_client-0.2.1.dist-info/METADATA
annuairesante_fhir_client-0.2.1.dist-info/WHEEL
annuairesante_fhir_client-0.2.1.dist-info/top_level.txt
annuairesante_fhir_client-0.2.1.dist-info/RECORD
