Metadata-Version: 2.4
Name: annuairesante-fhir-client
Version: 0.2.1
Summary: Client Python pour l'API FHIR de l'Annuaire Santé
Author: Annuaire Santé FHIR Client Contributors
License: MIT
Project-URL: Homepage, https://github.com/orochvilato/annuairesante-fhir-client
Project-URL: Documentation, https://github.com/orochvilato/annuairesante-fhir-client#readme
Project-URL: Repository, https://github.com/orochvilato/annuairesante-fhir-client
Project-URL: Bug Tracker, https://github.com/orochvilato/annuairesante-fhir-client/issues
Keywords: fhir,health,annuaire-sante,healthcare,france
Classifier: Development Status :: 4 - Beta
Classifier: Intended Audience :: Developers
Classifier: Intended Audience :: Healthcare Industry
Classifier: License :: OSI Approved :: MIT License
Classifier: Programming Language :: Python :: 3
Classifier: Programming Language :: Python :: 3.9
Classifier: Programming Language :: Python :: 3.10
Classifier: Programming Language :: Python :: 3.11
Classifier: Programming Language :: Python :: 3.12
Classifier: Topic :: Software Development :: Libraries :: Python Modules
Classifier: Topic :: Scientific/Engineering :: Medical Science Apps.
Requires-Python: >=3.9
License-File: LICENSE
Requires-Dist: httpx>=0.25.0
Requires-Dist: pydantic>=2.0.0
Requires-Dist: fhir.resources>=7.1.0
Requires-Dist: python-dotenv>=1.0.0
Requires-Dist: beautifulsoup4>=4.12.0
Requires-Dist: requests>=2.31.0
Provides-Extra: dev
Requires-Dist: pytest>=8.0.0; extra == "dev"
Requires-Dist: pytest-asyncio>=0.23.0; extra == "dev"
Requires-Dist: black>=24.0.0; extra == "dev"
Requires-Dist: ruff>=0.3.0; extra == "dev"
Dynamic: license-file
